pyalps-2.3.3.dist-info/RECORD
pyalps-2.3.3.dist-info/WHEEL
pyalps-2.3.3.dist-info/METADATA
pyalps-2.3.3.dist-info/licenses/LICENSE.txt
pyalps/pyngsrandom01_c.so
pyalps/mpl_setup_tk.py
pyalps/hlist.py
pyalps/pyngsresults_c.so
pyalps/pytools.py
pyalps/plot.py
pyalps/cxx.py
pyalps/pyngsapi_c.so
pyalps/pyngsobservables_c.so
pyalps/tools.py
pyalps/pyalea_c.so
pyalps/__init__.py
pyalps/maxent_c.so
pyalps/dict_intersect.py
pyalps/hdf5.py
pyalps/pytools_c.so
pyalps/alea_detail.py
pyalps/dataset.py
pyalps/dwa.py
pyalps/alea.py
pyalps/mpi.py
pyalps/pyalps_config.py
pyalps/maxent.py
pyalps/lattice.py
pyalps/fit_wrapper.py
pyalps/ngs.py
pyalps/pyngsresult_c.so
pyalps/cthyb.so
pyalps/mpl_setup_qt.py
pyalps/pyngshdf5_c.so
pyalps/math.py
pyalps/mpl_setup_macosx.py
pyalps/pyngsobservable_c.so
pyalps/dwa_c.so
pyalps/floatwitherror.py
pyalps/load.py
pyalps/ctint.so
pyalps/apptest.py
pyalps/pyngsbase_c.so
pyalps/pyngsparams_c.so
pyalps/pymcdata_c.so
pyalps/natural_sort.py
pyalps/plot_core.py
pyalps/bin/mps_meas
pyalps/bin/worm_evaluate
pyalps/bin/dwa
pyalps/bin/mps_optim
pyalps/bin/mps_compress
pyalps/bin/mps_apply_op
pyalps/bin/dirloop_sse
pyalps/bin/sparsediag
pyalps/bin/dmft
pyalps/bin/tebd
pyalps/bin/mps_overlap
pyalps/bin/qwl_evaluate
pyalps/bin/spinmc_evaluate
pyalps/bin/simplemc
pyalps/bin/worm
pyalps/bin/checksign
pyalps/bin/fulldiag
pyalps/bin/hybridization
pyalps/bin/dmrg
pyalps/bin/hirschfye
pyalps/bin/fulldiag_evaluate
pyalps/bin/spinmc
pyalps/bin/qwl
pyalps/bin/interaction
pyalps/bin/loop
pyalps/bin/mps_evolve
pyalps/xml/plot2xmgr.xsl
pyalps/xml/QMCXML2text.xsl
pyalps/xml/models.xml
pyalps/xml/plot2gp.xsl
pyalps/xml/archive2plot.xsl
pyalps/xml/lattices.xml
pyalps/xml/changestylesheet.xsl
pyalps/xml/helpers.xsl
pyalps/xml/plot2xsl.xsl
pyalps/xml/plot2mpl.xsl
pyalps/xml/plot2text.xsl
pyalps/xml/ALPS.xsl
pyalps/.dylibs/libhdf5.310.5.1.dylib
pyalps/.dylibs/libaec.0.1.3.dylib
pyalps/.dylibs/libgfortran.5.dylib
pyalps/.dylibs/libsz.2.0.1.dylib
pyalps/.dylibs/libhdf5_fortran.310.3.2.dylib
pyalps/.dylibs/libquadmath.0.dylib
