Metadata-Version: 2.2
Name: pyalps
Version: 2.3.3
Summary: Python Applications and Libraries for Physics Simulations
Author-Email: Sergei Iskakov <siskakov@umich.edu>
License: MIT License
Classifier: Development Status :: 5 - Production/Stable
Classifier: Intended Audience :: Science/Research
Classifier: Intended Audience :: Developers
Classifier: Programming Language :: C++
Classifier: Programming Language :: Python
Classifier: Programming Language :: Python :: 3
Classifier: Programming Language :: Python :: 3.9
Classifier: Programming Language :: Python :: 3.10
Classifier: Programming Language :: Python :: 3.11
Classifier: Programming Language :: Python :: 3.12
Classifier: Programming Language :: Python :: 3.13
Classifier: Programming Language :: Python :: 3 :: Only
Classifier: Programming Language :: Python :: Implementation :: CPython
Classifier: Operating System :: POSIX
Classifier: Operating System :: Unix
Classifier: Operating System :: MacOS
Project-URL: Homepage, https://alps.comp-phys.com
Project-URL: Issues, https://github.com/ALPSim/ALPS/issues
Requires-Python: >=3.9
Requires-Dist: numpy<2.1
Requires-Dist: scipy
Provides-Extra: tests
Requires-Dist: coverage>=5.0.3; extra == "tests"
Requires-Dist: pytest; extra == "tests"
Requires-Dist: pytest-benchmark[histogram]>=3.2.1; extra == "tests"
